mdclogpy/Logger.py
mdclogpy/__init__.py
mdclogpy-1.1.4.dist-info/METADATA
mdclogpy-1.1.4.dist-info/WHEEL
mdclogpy-1.1.4.dist-info/top_level.txt
mdclogpy-1.1.4.dist-info/RECORD
