Metadata-Version: 2.1
Name: mdclogpy
Version: 1.1.4
Summary: Structured logging library with Mapped Diagnostic Context
Home-page: https://gerrit.o-ran-sc.org/r/admin/repos/com/pylog
Author: kturunen
Author-email: kturunen@nokia.com
License: Apache Software License
Platform: UNKNOWN
Classifier: Development Status :: 5 - Production/Stable
Classifier: License :: OSI Approved :: Apache Software License
Classifier: Programming Language :: Python :: 3 :: Only
Classifier: Topic :: Software Development :: Libraries :: Python Modules
